dataformat/__init__.py
dataformat-0.1.1.dist-info/DESCRIPTION.rst
dataformat-0.1.1.dist-info/METADATA
dataformat-0.1.1.dist-info/RECORD
dataformat-0.1.1.dist-info/WHEEL
dataformat-0.1.1.dist-info/metadata.json
dataformat-0.1.1.dist-info/top_level.txt
