Metadata-Version: 2.0
Name: dataformat
Version: 0.1.1
Summary: Simple format check and cleanup utility
Home-page: http://github.com/g3rb3n/dataformat
Author: Gerben van Eerten
Author-email: gerben@eerten.com
License: MIT
Keywords: development
Platform: UNKNOWN
Classifier: Development Status :: 3 - Alpha
Classifier: Intended Audience :: Developers
Classifier: Topic :: Software Development :: Build Tools
Classifier: License :: OSI Approved :: MIT License
Classifier: Programming Language :: Python :: 3
Classifier: Programming Language :: Python :: 3.2
Classifier: Programming Language :: Python :: 3.3
Classifier: Programming Language :: Python :: 3.4
Requires-Python: >=3
